pylandscape/__init__.py
pylandscape/cka.py
pylandscape/hessian.py
pylandscape/mc_utils/__init__.py
pylandscape/mc_utils/curve_converter.py
pylandscape/mc_utils/curve_module.py
pylandscape/mc_utils/curve_net.py
pylandscape/mc_utils/curves.py
pylandscape/mc_utils/train_curve.py
pylandscape/metric.py
pylandscape/mode_connectivity.py
pylandscape/neural_efficiency.py
pylandscape/surface.py
pylandscape-0.0.18.dist-info/LICENSE.txt
pylandscape-0.0.18.dist-info/METADATA
pylandscape-0.0.18.dist-info/WHEEL
pylandscape-0.0.18.dist-info/RECORD
