Metadata-Version: 2.3
Name: pylandscape
Version: 0.0.18
Summary: Python package to explore the loss landscape of Machine Learning models
License: MIT
Author: Tommaso Baldi
Author-email: tommaso.baldi@santannapisa.it
Requires-Python: >=3.9,<4.0
Classifier: License :: OSI Approved :: MIT License
Classifier: Programming Language :: Python :: 3
Classifier: Programming Language :: Python :: 3.9
Classifier: Programming Language :: Python :: 3.10
Classifier: Programming Language :: Python :: 3.11
Classifier: Programming Language :: Python :: 3.12
Classifier: Programming Language :: Python :: 3.13
Requires-Dist: PyHessian
Requires-Dist: numpy (==1.24.4)
Requires-Dist: pandas
Requires-Dist: scipy
Requires-Dist: torch (==2.3.0)
Requires-Dist: tqdm
Requires-Dist: vtk (==9.4.1)
Project-URL: Homepage, https://github.com/balditommaso/PyLandscape
Project-URL: Repository, https://github.com/balditommaso/PyLandscape
